ancilla/.gitignore
ancilla/__init__.py
ancilla/backtesting/__init__.py
ancilla/backtesting/configuration.py
ancilla/backtesting/engine.py
ancilla/backtesting/portfolio.py
ancilla/backtesting/results.py
ancilla/backtesting/strategy.py
ancilla/formulae/__init__.py
ancilla/formulae/indicators.py
ancilla/formulae/metrics.py
ancilla/formulae/options.py
ancilla/formulae/volatility.py
ancilla/models/__init__.py
ancilla/models/bar_data.py
ancilla/models/instruments.py
ancilla/models/market_data.py
ancilla/models/market_snapshot.py
ancilla/models/option_data.py
ancilla/models/position.py
ancilla/models/trade.py
ancilla/providers/__init__.py
ancilla/providers/fred.py
ancilla/providers/polygon.py
ancilla/requirements.txt
ancilla/tests/__init__.py
ancilla/tests/test_portfolio.py
ancilla/tests/test_providers_polygon.py
ancilla/utils/__init__.py
ancilla/utils/caching.py
ancilla/utils/logging.py
ancilla/visualizations/__init__.py
ancilla/visualizations/market.py
ancilla-1.1.1.dist-info/LICENSE.txt
ancilla-1.1.1.dist-info/METADATA
ancilla-1.1.1.dist-info/WHEEL
ancilla-1.1.1.dist-info/RECORD
