Metadata-Version: 2.1
Name: ancilla
Version: 1.1.1
Summary: Ancilla is a Python library for quantitative finance.
Author: Sid Garimella
Author-email: gsidsid@gmail.com
Requires-Python: >=3.8,<4.0
Classifier: Programming Language :: Python :: 3
Classifier: Programming Language :: Python :: 3.8
Classifier: Programming Language :: Python :: 3.9
Classifier: Programming Language :: Python :: 3.10
Classifier: Programming Language :: Python :: 3.11
Requires-Dist: fredapi (>=0.5.2)
Requires-Dist: numpy (>=1.22.0)
Requires-Dist: pandas (>=1.5.0)
Requires-Dist: plotly (>=5.24.1)
Requires-Dist: polygon-api-client (>=1.12.0)
Requires-Dist: pytz
Requires-Dist: scipy (>=1.9.0)
